consulate/__init__.py
consulate/adapters.py
consulate/cli.py
consulate/exceptions.py
consulate/utils.py
consulate/api/__init__.py
consulate/api/acl.py
consulate/api/agent.py
consulate/api/base.py
consulate/api/catalog.py
consulate/api/event.py
consulate/api/health.py
consulate/api/kv.py
consulate/api/session.py
consulate/api/status.py
consulate-0.6.0.dist-info/zip-safe
consulate-0.6.0.dist-info/top_level.txt
consulate-0.6.0.dist-info/entry_points.txt
consulate-0.6.0.dist-info/METADATA
consulate-0.6.0.dist-info/DESCRIPTION.rst
consulate-0.6.0.dist-info/metadata.json
consulate-0.6.0.dist-info/WHEEL
consulate-0.6.0.dist-info/RECORD
