Metadata-Version: 2.0
Name: consulate
Version: 0.6.0
Summary: A Client library for the Consul
Home-page: https://consulate.readthedocs.org
Author: Gavin M. Roy
Author-email: gavinr@aweber.com
License: BSD
Platform: UNKNOWN
Classifier: Development Status :: 4 - Beta
Classifier: Intended Audience :: Developers
Classifier: License :: OSI Approved :: BSD License
Classifier: Operating System :: OS Independent
Classifier: Programming Language :: Python :: 2
Classifier: Programming Language :: Python :: 2.6
Classifier: Programming Language :: Python :: 2.7
Classifier: Programming Language :: Python :: 3
Classifier: Programming Language :: Python :: 3.3
Classifier: Programming Language :: Python :: 3.4
Classifier: Programming Language :: Python :: Implementation :: CPython
Classifier: Programming Language :: Python :: Implementation :: PyPy
Classifier: Topic :: System :: Systems Administration
Classifier: Topic :: System :: Clustering
Classifier: Topic :: Internet :: WWW/HTTP
Classifier: Topic :: Software Development :: Libraries
Requires-Dist: requests (>=2.0.0,<3.0.0)
Provides-Extra: unixsocket
Requires-Dist: requests-unixsocket (>=0.1.4,<=1.0.0); extra == 'unixsocket'
